README.md
setup.cfg
setup.py
ca2spike/__init__.py
ca2spike/main.py
ca2spike.egg-info/PKG-INFO
ca2spike.egg-info/SOURCES.txt
ca2spike.egg-info/dependency_links.txt
ca2spike.egg-info/entry_points.txt
ca2spike.egg-info/top_level.txt
ca2spike/data/model_tensorflow.h5
ca2spike/data/model_theano.h5
ca2spike/data/weights_tensorflow.h5