Metadata-Version: 1.1
Name: ca2spike
Version: 0.1.2
Summary: convert calcium trace to spikes
Home-page: UNKNOWN
Author: UNKNOWN
Author-email: UNKNOWN
License: UNKNOWN
Platform: UNKNOWN
Requires: numpy
Requires: uifunc
